tensor_visualizer/__init__.py
tensor_visualizer/tensor_visualizer.py
tensor_visualizer/static/bundle.js
tensor_visualizer-0.1.0.dist-info/METADATA
tensor_visualizer-0.1.0.dist-info/WHEEL
tensor_visualizer-0.1.0.dist-info/licenses/LICENSE
tensor_visualizer-0.1.0.dist-info/RECORD
