Metadata-Version: 2.3
Name: tensor-visualizer
Version: 0.1.0
Summary: A Jupyter widget for visualizing tensors as heatmaps.
Project-URL: homepage, https://github.com/apple/tensor-visualizer
Author-email: Donghao Ren <donghao@apple.com>
License: Copyright © 2024 Apple Inc. All rights reserved.
License-File: LICENSE
Classifier: Operating System :: OS Independent
Classifier: Programming Language :: Python :: 3
Requires-Python: >=3.7
Requires-Dist: anywidget
Requires-Dist: numpy
